README.txt
setup.py
inquant/__init__.py
inquant.contentmirror.base.egg-info/PKG-INFO
inquant.contentmirror.base.egg-info/SOURCES.txt
inquant.contentmirror.base.egg-info/dependency_links.txt
inquant.contentmirror.base.egg-info/entry_points.txt
inquant.contentmirror.base.egg-info/namespace_packages.txt
inquant.contentmirror.base.egg-info/not-zip-safe
inquant.contentmirror.base.egg-info/requires.txt
inquant.contentmirror.base.egg-info/top_level.txt
inquant/contentmirror/__init__.py
inquant/contentmirror/base/CHANGELOG
inquant/contentmirror/base/README.rst
inquant/contentmirror/base/__init__.py
inquant/contentmirror/base/configure.zcml
inquant/contentmirror/base/interfaces.py
inquant/contentmirror/base/locator.py
inquant/contentmirror/base/manager.py
inquant/contentmirror/base/subscriber.py
inquant/contentmirror/base/traverser.py
inquant/contentmirror/base/utils.py
inquant/contentmirror/base/tests/__init__.py
inquant/contentmirror/base/tests/base.py
inquant/contentmirror/base/tests/test_doctests.py
inquant/contentmirror/base/tests/test_refmgr.py
inquant/contentmirror/base/tests/test_traverser.py