Metadata-Version: 1.0
Name: inquant.contentmirror.base
Version: 0.2
Summary: mirror plone content transparently in a plone site
Home-page: https://svn.plone.org/svn/collective/inquant.contentmirror.base/trunk
Author: Stefan Eletzhofer
Author-email: stefan.eletzhofer@inquant.de
License: GPL
Platform: UNKNOWN
Classifier: Framework :: Plone
Classifier: Framework :: Zope2
Classifier: Framework :: Zope3
Classifier: Programming Language :: Python
Classifier: Topic :: Software Development :: Libraries :: Python Modules
